genesis_metallicity/__init__.py
genesis_metallicity/genesis_metallicity.py
genesis_metallicity/version.py
genesis_metallicity/data/__init__.py
genesis_metallicity/data/data_metallicity.pkl
genesis_metallicity/data/data_metallicity_noEWHb.pkl
genesis_metallicity/data/data_temperature.pkl
genesis_metallicity/data/lines.py
genesis_metallicity/dust/__init__.py
genesis_metallicity/dust/attenuation.py
genesis_metallicity/dust/extinction_correction.py
genesis_metallicity/metallicity/__init__.py
genesis_metallicity/metallicity/direct_method.py
genesis_metallicity/metallicity/strong_method.py
genesis_metallicity/metallicity/strong_method_noEWHb.py
genesis_metallicity/temperature/__init__.py
genesis_metallicity/temperature/temperature_estimator.py
genesis_metallicity-1.4.0.dist-info/LICENSE
genesis_metallicity-1.4.0.dist-info/METADATA
genesis_metallicity-1.4.0.dist-info/WHEEL
genesis_metallicity-1.4.0.dist-info/top_level.txt
genesis_metallicity-1.4.0.dist-info/RECORD
