Metadata-Version: 2.1
Name: genesis_metallicity
Version: 1.4.0
Summary: non-parametric gas-phase metallicity and electron temperature estimation
Home-page: https://github.com/langeroodi/genesis_metallicity
Author: Danial Langeroodi
Author-email: dlangaroudi@gmail.com
License: MIT
Classifier: Programming Language :: Python :: 3
Classifier: License :: OSI Approved :: MIT License
Classifier: Operating System :: OS Independent
Requires-Python: >=3.6
License-File: LICENSE
Requires-Dist: setuptools
Requires-Dist: numpy
Requires-Dist: scipy
Requires-Dist: h5py
Requires-Dist: astropy
Requires-Dist: matplotlib
Requires-Dist: uncertainties
Requires-Dist: PyNeb
